{
  "created": "2026-07-12T18:14:39+00:00",
  "seasons": [
    2012,
    2025
  ],
  "test_seasons": [
    2023,
    2024,
    2025
  ],
  "scoring": "ppr",
  "results": [
    {
      "position": "QB",
      "mae": 6.170402881314858,
      "rmse": 7.881643053051351,
      "n": 663,
      "model": "naive_last4",
      "test_season": 2023,
      "pinball_p10": null,
      "pinball_p50": null,
      "pinball_p90": null,
      "coverage_p10_p90": null
    },
    {
      "position": "RB",
      "mae": 4.395929911068048,
      "rmse": 6.27234259774691,
      "n": 1570,
      "model": "naive_last4",
      "test_season": 2023,
      "pinball_p10": null,
      "pinball_p50": null,
      "pinball_p90": null,
      "coverage_p10_p90": null
    },
    {
      "position": "TE",
      "mae": 3.7164124382318393,
      "rmse": 5.093917734979484,
      "n": 1188,
      "model": "naive_last4",
      "test_season": 2023,
      "pinball_p10": null,
      "pinball_p50": null,
      "pinball_p90": null,
      "coverage_p10_p90": null
    },
    {
      "position": "WR",
      "mae": 4.670632234993059,
      "rmse": 6.561806851582923,
      "n": 2472,
      "model": "naive_last4",
      "test_season": 2023,
      "pinball_p10": null,
      "pinball_p50": null,
      "pinball_p90": null,
      "coverage_p10_p90": null
    },
    {
      "position": "OVERALL",
      "mae": 4.573814344512278,
      "rmse": 6.384599728545356,
      "n": 5893,
      "model": "naive_last4",
      "test_season": 2023,
      "pinball_p10": null,
      "pinball_p50": null,
      "pinball_p90": null,
      "coverage_p10_p90": null
    },
    {
      "position": "QB",
      "mae": 6.006694638934071,
      "rmse": 7.477946073995146,
      "n": 663,
      "model": "xgboost",
      "test_season": 2023,
      "pinball_p10": null,
      "pinball_p50": null,
      "pinball_p90": null,
      "coverage_p10_p90": null
    },
    {
      "position": "RB",
      "mae": 4.313119766411508,
      "rmse": 5.9655318707161005,
      "n": 1570,
      "model": "xgboost",
      "test_season": 2023,
      "pinball_p10": null,
      "pinball_p50": null,
      "pinball_p90": null,
      "coverage_p10_p90": null
    },
    {
      "position": "TE",
      "mae": 3.4705019612946493,
      "rmse": 4.734546733131641,
      "n": 1188,
      "model": "xgboost",
      "test_season": 2023,
      "pinball_p10": null,
      "pinball_p50": null,
      "pinball_p90": null,
      "coverage_p10_p90": null
    },
    {
      "position": "WR",
      "mae": 4.5157115441425715,
      "rmse": 6.196206881602798,
      "n": 2472,
      "model": "xgboost",
      "test_season": 2023,
      "pinball_p10": null,
      "pinball_p50": null,
      "pinball_p90": null,
      "coverage_p10_p90": null
    },
    {
      "position": "OVERALL",
      "mae": 4.418773433907659,
      "rmse": 6.032954438678694,
      "n": 5893,
      "model": "xgboost",
      "test_season": 2023,
      "pinball_p10": null,
      "pinball_p50": null,
      "pinball_p90": null,
      "coverage_p10_p90": null
    },
    {
      "position": "QB",
      "mae": 6.128383310802877,
      "rmse": 7.688232602104628,
      "n": 663,
      "model": "transformer",
      "test_season": 2023,
      "pinball_p10": 1.2196739472921259,
      "pinball_p50": 3.0641916554014386,
      "pinball_p90": 1.4278587560265308,
      "coverage_p10_p90": 0.7873303167420814
    },
    {
      "position": "RB",
      "mae": 4.351972898719749,
      "rmse": 6.799593616035831,
      "n": 1570,
      "model": "transformer",
      "test_season": 2023,
      "pinball_p10": 0.7191036614486866,
      "pinball_p50": 2.1759864493598746,
      "pinball_p90": 1.4012531962218557,
      "coverage_p10_p90": 0.9445859872611465
    },
    {
      "position": "TE",
      "mae": 3.4261466472352597,
      "rmse": 5.162652240290338,
      "n": 1188,
      "model": "transformer",
      "test_season": 2023,
      "pinball_p10": 0.5256311034900278,
      "pinball_p50": 1.7130733236176299,
      "pinball_p90": 1.0176469120136413,
      "coverage_p10_p90": 0.9031986531986532
    },
    {
      "position": "WR",
      "mae": 4.282264015308437,
      "rmse": 6.526748453859285,
      "n": 2472,
      "model": "transformer",
      "test_season": 2023,
      "pinball_p10": 0.68064880336932,
      "pinball_p50": 2.1411320076542184,
      "pinball_p90": 1.2877114733071773,
      "coverage_p10_p90": 0.88915857605178
    },
    {
      "position": "OVERALL",
      "mae": 4.335946792603132,
      "rmse": 6.496934134430174,
      "n": 5893,
      "model": "transformer",
      "test_season": 2023,
      "pinball_p10": 0.7202868095035175,
      "pinball_p50": 2.167973396301566,
      "pinball_p90": 1.2792847729172665,
      "coverage_p10_p90": 0.8952995078907178
    },
    {
      "position": "QB",
      "mae": 6.514048613677614,
      "rmse": 8.31646770540511,
      "n": 664,
      "model": "naive_last4",
      "test_season": 2024,
      "pinball_p10": null,
      "pinball_p50": null,
      "pinball_p90": null,
      "coverage_p10_p90": null
    },
    {
      "position": "RB",
      "mae": 4.483088376263835,
      "rmse": 6.268281937426974,
      "n": 1606,
      "model": "naive_last4",
      "test_season": 2024,
      "pinball_p10": null,
      "pinball_p50": null,
      "pinball_p90": null,
      "coverage_p10_p90": null
    },
    {
      "position": "TE",
      "mae": 3.7275419826458718,
      "rmse": 5.12343969502403,
      "n": 1223,
      "model": "naive_last4",
      "test_season": 2024,
      "pinball_p10": null,
      "pinball_p50": null,
      "pinball_p90": null,
      "coverage_p10_p90": null
    },
    {
      "position": "WR",
      "mae": 4.770209101588796,
      "rmse": 6.69990081538656,
      "n": 2427,
      "model": "naive_last4",
      "test_season": 2024,
      "pinball_p10": null,
      "pinball_p50": null,
      "pinball_p90": null,
      "coverage_p10_p90": null
    },
    {
      "position": "OVERALL",
      "mae": 4.6725083692725615,
      "rmse": 6.499411128343314,
      "n": 5920,
      "model": "naive_last4",
      "test_season": 2024,
      "pinball_p10": null,
      "pinball_p50": null,
      "pinball_p90": null,
      "coverage_p10_p90": null
    },
    {
      "position": "QB",
      "mae": 6.3451895869209105,
      "rmse": 7.889130022762541,
      "n": 664,
      "model": "xgboost",
      "test_season": 2024,
      "pinball_p10": null,
      "pinball_p50": null,
      "pinball_p90": null,
      "coverage_p10_p90": null
    },
    {
      "position": "RB",
      "mae": 4.351089221956128,
      "rmse": 6.001146580241622,
      "n": 1606,
      "model": "xgboost",
      "test_season": 2024,
      "pinball_p10": null,
      "pinball_p50": null,
      "pinball_p90": null,
      "coverage_p10_p90": null
    },
    {
      "position": "TE",
      "mae": 3.5622398939662943,
      "rmse": 4.835850113177632,
      "n": 1223,
      "model": "xgboost",
      "test_season": 2024,
      "pinball_p10": null,
      "pinball_p50": null,
      "pinball_p90": null,
      "coverage_p10_p90": null
    },
    {
      "position": "WR",
      "mae": 4.631356058141358,
      "rmse": 6.354395018156339,
      "n": 2427,
      "model": "xgboost",
      "test_season": 2024,
      "pinball_p10": null,
      "pinball_p50": null,
      "pinball_p90": null,
      "coverage_p10_p90": null
    },
    {
      "position": "OVERALL",
      "mae": 4.5266850877714315,
      "rmse": 6.1754062234769,
      "n": 5920,
      "model": "xgboost",
      "test_season": 2024,
      "pinball_p10": null,
      "pinball_p50": null,
      "pinball_p90": null,
      "coverage_p10_p90": null
    },
    {
      "position": "QB",
      "mae": 6.327227514128549,
      "rmse": 8.202385898717456,
      "n": 664,
      "model": "transformer",
      "test_season": 2024,
      "pinball_p10": 1.1893366558622702,
      "pinball_p50": 3.1636137570642746,
      "pinball_p90": 1.5120783809696334,
      "coverage_p10_p90": 0.8253012048192772
    },
    {
      "position": "RB",
      "mae": 4.39869495636961,
      "rmse": 6.834163622401402,
      "n": 1606,
      "model": "transformer",
      "test_season": 2024,
      "pinball_p10": 0.7141068202873524,
      "pinball_p50": 2.199347478184805,
      "pinball_p90": 1.3833623251273652,
      "coverage_p10_p90": 0.9259028642590287
    },
    {
      "position": "TE",
      "mae": 3.4920668665403145,
      "rmse": 5.289309831638583,
      "n": 1223,
      "model": "transformer",
      "test_season": 2024,
      "pinball_p10": 0.5201442329377327,
      "pinball_p50": 1.7460334332701573,
      "pinball_p90": 1.0330333080985754,
      "coverage_p10_p90": 0.892886345053148
    },
    {
      "position": "WR",
      "mae": 4.460301920498518,
      "rmse": 6.733586295151238,
      "n": 2427,
      "model": "transformer",
      "test_season": 2024,
      "pinball_p10": 0.6869787430947499,
      "pinball_p50": 2.230150960249259,
      "pinball_p90": 1.3289740060535926,
      "coverage_p10_p90": 0.8706221672847136
    },
    {
      "position": "OVERALL",
      "mae": 4.45296177502359,
      "rmse": 6.677178849898723,
      "n": 5920,
      "model": "transformer",
      "test_season": 2024,
      "pinball_p10": 0.7162177194675404,
      "pinball_p50": 2.226480887511795,
      "pinball_p90": 1.303128308718752,
      "coverage_p10_p90": 0.8851351351351351
    },
    {
      "position": "QB",
      "mae": 7.034261568087577,
      "rmse": 8.844057176955591,
      "n": 664,
      "model": "naive_last4",
      "test_season": 2025,
      "pinball_p10": null,
      "pinball_p50": null,
      "pinball_p90": null,
      "coverage_p10_p90": null
    },
    {
      "position": "RB",
      "mae": 4.44784123121798,
      "rmse": 6.396954436526832,
      "n": 1650,
      "model": "naive_last4",
      "test_season": 2025,
      "pinball_p10": null,
      "pinball_p50": null,
      "pinball_p90": null,
      "coverage_p10_p90": null
    },
    {
      "position": "TE",
      "mae": 3.813053050299825,
      "rmse": 5.465195162310548,
      "n": 1283,
      "model": "naive_last4",
      "test_season": 2025,
      "pinball_p10": null,
      "pinball_p50": null,
      "pinball_p90": null,
      "coverage_p10_p90": null
    },
    {
      "position": "WR",
      "mae": 4.432441076118915,
      "rmse": 6.1835500498094165,
      "n": 2498,
      "model": "naive_last4",
      "test_season": 2025,
      "pinball_p10": null,
      "pinball_p50": null,
      "pinball_p90": null,
      "coverage_p10_p90": null
    },
    {
      "position": "OVERALL",
      "mae": 4.589675567579909,
      "rmse": 6.446490426858326,
      "n": 6095,
      "model": "naive_last4",
      "test_season": 2025,
      "pinball_p10": null,
      "pinball_p50": null,
      "pinball_p90": null,
      "coverage_p10_p90": null
    },
    {
      "position": "QB",
      "mae": 6.687885508314673,
      "rmse": 8.189880349993865,
      "n": 664,
      "model": "xgboost",
      "test_season": 2025,
      "pinball_p10": null,
      "pinball_p50": null,
      "pinball_p90": null,
      "coverage_p10_p90": null
    },
    {
      "position": "RB",
      "mae": 4.318937723685756,
      "rmse": 6.046892638645364,
      "n": 1650,
      "model": "xgboost",
      "test_season": 2025,
      "pinball_p10": null,
      "pinball_p50": null,
      "pinball_p90": null,
      "coverage_p10_p90": null
    },
    {
      "position": "TE",
      "mae": 3.5781096512771455,
      "rmse": 5.017570916537513,
      "n": 1283,
      "model": "xgboost",
      "test_season": 2025,
      "pinball_p10": null,
      "pinball_p50": null,
      "pinball_p90": null,
      "coverage_p10_p90": null
    },
    {
      "position": "WR",
      "mae": 4.269815956971663,
      "rmse": 5.7978753225973865,
      "n": 2498,
      "model": "xgboost",
      "test_season": 2025,
      "pinball_p10": null,
      "pinball_p50": null,
      "pinball_p90": null,
      "coverage_p10_p90": null
    },
    {
      "position": "OVERALL",
      "mae": 4.4009381730445005,
      "rmse": 6.023488715907926,
      "n": 6095,
      "model": "xgboost",
      "test_season": 2025,
      "pinball_p10": null,
      "pinball_p50": null,
      "pinball_p90": null,
      "coverage_p10_p90": null
    },
    {
      "position": "QB",
      "mae": 6.61270462199148,
      "rmse": 8.316033679562858,
      "n": 664,
      "model": "transformer",
      "test_season": 2025,
      "pinball_p10": 1.23309580367063,
      "pinball_p50": 3.30635231099574,
      "pinball_p90": 1.6389372967553424,
      "coverage_p10_p90": 0.8117469879518072
    },
    {
      "position": "RB",
      "mae": 4.209234281706901,
      "rmse": 6.766753186212482,
      "n": 1650,
      "model": "transformer",
      "test_season": 2025,
      "pinball_p10": 0.6950771924203568,
      "pinball_p50": 2.1046171408534504,
      "pinball_p90": 1.3849409316577332,
      "coverage_p10_p90": 0.9290909090909091
    },
    {
      "position": "TE",
      "mae": 3.439612585752041,
      "rmse": 5.379992069190888,
      "n": 1283,
      "model": "transformer",
      "test_season": 2025,
      "pinball_p10": 0.5325738749919302,
      "pinball_p50": 1.7198062928760205,
      "pinball_p90": 1.0779823714291221,
      "coverage_p10_p90": 0.911925175370226
    },
    {
      "position": "WR",
      "mae": 4.028729880650671,
      "rmse": 6.119209296949466,
      "n": 2498,
      "model": "transformer",
      "test_season": 2025,
      "pinball_p10": 0.6190337265549097,
      "pinball_p50": 2.0143649403253354,
      "pinball_p90": 1.2631466270439904,
      "coverage_p10_p90": 0.8863090472377902
    },
    {
      "position": "OVERALL",
      "mae": 4.235088207252498,
      "rmse": 6.431874303119124,
      "n": 6095,
      "model": "transformer",
      "test_season": 2025,
      "pinball_p10": 0.6883169010138962,
      "pinball_p50": 2.117544103626249,
      "pinball_p90": 1.2980801573716585,
      "coverage_p10_p90": 0.8951599671862183
    }
  ]
}